{
 "Accuracy": 10.63,
 "Time": [
  123.10258886000001,
  2.55934814242562,
  372.688744716
 ],
 "Optimizer": {
  "Meta": {
   "optim": "Adam",
   "lr": 0.01
  },
  "Inner": {
   "optim": "SGD",
   "lr": 0.1,
   "momentum": 0.9
  }
 },
 "Device": "GeForce GTX 1080 Ti",
 "Param_names": [
  "Identity",
  "FlipUD",
  "FlipLR",
  "Rotate",
  "TranslateX",
  "TranslateY",
  "ShearX",
  "ShearY",
  "Contrast",
  "Color",
  "Brightness",
  "Sharpness",
  "Posterize",
  "Solarize"
 ],
 "Log": [
  {
   "epoch": 1,
   "train_loss": 4.621213912963867,
   "val_loss": 2.6058712005615234,
   "acc": 10.63,
   "time": 119.48313626099997,
   "param": [
    {
     "p": 0.015274659730494022,
     "m": 1.0
    },
    {
     "p": 0.02458246424794197,
     "m": 1.0
    },
    {
     "p": 0.11483544856309891,
     "m": 1.0
    },
    {
     "p": 0.04223901778459549,
     "m": 1.0
    },
    {
     "p": 0.11209841817617416,
     "m": 1.0
    },
    {
     "p": 0.04026665911078453,
     "m": 1.0
    },
    {
     "p": 0.11058749258518219,
     "m": 1.0
    },
    {
     "p": 0.11480649560689926,
     "m": 1.0
    },
    {
     "p": 0.06525973230600357,
     "m": 1.0
    },
    {
     "p": 0.0905124843120575,
     "m": 1.0
    },
    {
     "p": 0.11407123506069183,
     "m": 1.0
    },
    {
     "p": 0.02507488988339901,
     "m": 1.0
    },
    {
     "p": 0.06955452263355255,
     "m": 1.0
    },
    {
     "p": 0.06083643063902855,
     "m": 1.0
    }
   ]
  },
  {
   "epoch": 2,
   "train_loss": 599.9815673828125,
   "val_loss": 537.0701293945312,
   "acc": 10.0,
   "time": 124.92047199100006,
   "param": [
    {
     "p": 0.0011777246836572886,
     "m": 1.0
    },
    {
     "p": 0.0007173393969424069,
     "m": 1.0
    },
    {
     "p": 0.16452042758464813,
     "m": 1.0
    },
    {
     "p": 0.0007173393969424069,
     "m": 1.0
    },
    {
     "p": 0.05033645033836365,
     "m": 1.0
    },
    {
     "p": 0.0007173393969424069,
     "m": 1.0
    },
    {
     "p": 0.0011522152926772833,
     "m": 1.0
    },
    {
     "p": 0.3963681757450104,
     "m": 1.0
    },
    {
     "p": 0.0011067679151892662,
     "m": 1.0
    },
    {
     "p": 0.16967317461967468,
     "m": 1.0
    },
    {
     "p": 0.0007173393969424069,
     "m": 1.0
    },
    {
     "p": 0.0007173393969424069,
     "m": 1.0
    },
    {
     "p": 0.21081382036209106,
     "m": 1.0
    },
    {
     "p": 0.0012645238311961293,
     "m": 1.0
    }
   ]
  },
  {
   "epoch": 3,
   "train_loss": 64.64898681640625,
   "val_loss": 312.3837890625,
   "acc": 10.0,
   "time": 124.904158328,
   "param": [
    {
     "p": 0.0007209536270238459,
     "m": 1.0
    },
    {
     "p": 0.0007209536270238459,
     "m": 1.0
    },
    {
     "p": 0.0007209536270238459,
     "m": 1.0
    },
    {
     "p": 0.0007209536270238459,
     "m": 1.0
    },
    {
     "p": 0.0007209536270238459,
     "m": 1.0
    },
    {
     "p": 0.0027082031592726707,
     "m": 1.0
    },
    {
     "p": 0.0007209536270238459,
     "m": 1.0
    },
    {
     "p": 0.7853431105613708,
     "m": 1.0
    },
    {
     "p": 0.02059904858469963,
     "m": 1.0
    },
    {
     "p": 0.0583711601793766,
     "m": 1.0
    },
    {
     "p": 0.001522295642644167,
     "m": 1.0
    },
    {
     "p": 0.0007209536270238459,
     "m": 1.0
    },
    {
     "p": 0.12568853795528412,
     "m": 1.0
    },
    {
     "p": 0.0007209536270238459,
     "m": 1.0
    }
   ]
  }
 ]
}